[{"s": "air-balance-mercedes-kak-rabotaet", "t": "Air Balance Mercedes: как работает и настройка ароматов", "i": "📁", "c": "s-class"}, {"s": "airflow-toggle-perevod", "t": "Airflow Toggle в Mercedes: перевод, функции и настройка", "i": "📁", "c": "e-class"}, {"s": "air-balance-mercedes", "t": "Air Balance Mercedes: Ароматизация салона и её особенности", "i": "📁", "c": null}, {"s": "airmatic-mercedes-chto-eto", "t": "Airmatic Mercedes: что это, устройство, поломки и ресурс", "i": "📁", "c": "s-class"}, {"s": "aimol-oil-club", "t": "AIMOL Oil Club: Экспертный обзор масел, отзывы и характеристики", "i": "📁", "c": null}, {"s": "air-care-climatronic-chto-eto-takoe-tiguan", "t": "Air Care Climatronic в Тигуане: устройство, коды ошибок и ремонт", "i": "📁", "c": "drugoe"}, {"s": "air-care-climatronic-volkswagen-chto-eto-takoe", "t": "Air Care Climatronic Volkswagen: что это и как работает", "i": "📁", "c": "drugoe"}, {"s": "air-care-climatronic", "t": "Air Care Climatronic: Полный обзор системы климата Volkswagen", "i": "📁", "c": "g-class"}, {"s": "air-balance-mercedes-kupit", "t": "Air Balance Mercedes купить: где найти и как заправить", "i": "📁", "c": "s-class"}, {"s": "airmatic-visit-workshop-w220", "t": "Airmatic W220: Диагностика, ошибки и ремонт подвески Mercedes", "i": "📁", "c": "s-class"}, {"s": "air-balance-mercedes-ustanovka", "t": "Air Balance в Mercedes: установка, настройка и нюансы (2026)", "i": "📁", "c": "e-class"}, {"s": "air-care-climatronic-chto-eto", "t": "Air Care Climatronic: что это за система и как она работает в авто", "i": "📁", "c": "drugoe"}, {"s": "airwick-ili-glade-chto-luchshe", "t": "Air Wick или Glade: что лучше для дома в 2026 году? Сравнение и отзывы", "i": "📁", "c": "drugoe"}, {"s": "airline-cyclone-3", "t": "Airline Cyclone 3: обзор, настройка и ремонт — полное руководство 2026", "i": "📁", "c": "drugoe"}, {"s": "airline-cyclone-2-otzyvy", "t": "Airline Cyclone 2: честные отзывы владельцев и экспертный разбор", "i": "📁", "c": "drugoe"}, {"s": "airline-vca-03-cyclone-turbo", "t": "Airline VCA-03 Cyclone Turbo: обзор, настройка и ремонт пылесоса", "i": "📁", "c": "drugoe"}, {"s": "airline-cyclone-turbo", "t": "Airline Cyclone Turbo: обзор, характеристики и секреты тюнинга", "i": "📁", "c": "drugoe"}, {"s": "airline-cyclone-turbo-vca-03", "t": "Airline Cyclone Turbo VCA-03: обзор, настройка и ремонт автопылесоса", "i": "📁", "c": "drugoe"}, {"s": "airline-cyclone-turbo-avtomobilnyj-pylesos", "t": "Cyclone Turbo автомобильный пылесос: обзор, характеристики и тест", "i": "📁", "c": "drugoe"}, {"s": "air-clean-perevod", "t": "Air Clean перевод: что это и как работает в авто?", "i": "📁", "c": "drugoe"}, {"s": "airmatic-vehicle-rising", "t": "AirMatic Vehicle Rising: почему кузов поднимается сам", "i": "📁", "c": "s-class"}]