[{"s": "cibertrak-tesla-tsena", "t": "CiberTrak Tesla: цена, комплектации и где купить в 2026 году", "i": "📁", "c": "drugoe"}, {"s": "circle-in-the-sand-belinda-karlajl-perevod", "t": "Circle in the Sand: перевод Белинды Карлайл и история хита", "i": "📁", "c": "drugoe"}, {"s": "ci-4-sl-rasshifrovka-masla", "t": "Расшифровка масла CI-4: характеристики, классификация и применение", "i": "📁", "c": "drugoe"}, {"s": "ciclop-3d-scanner", "t": "Ciclop 3D Scanner: Полный обзор, сборка и настройка", "i": "📁", "c": "drugoe"}, {"s": "citroen-club-ru", "t": "Citroen Club RU: Всё о клубах и сообществах владельцев Citroen", "i": "📁", "c": "drugoe"}, {"s": "citan-mercedes-kupit", "t": "Mercedes-Benz Citan купить: цена, обзор, комплектации и отзывы", "i": "📁", "c": "b-class"}, {"s": "cif-single-chip-drajver-skachat-windows-10-genius-web-camera", "t": "CIF Single Chip драйвер для Genius Web Camera на Windows 10: скачать и установить", "i": "📁", "c": "drugoe"}, {"s": "citroens-club-ru", "t": "Citroën Club Russia: сообщество, модели и советы владельцам", "i": "📁", "c": "drugoe"}, {"s": "circle-in-the-sand-belinda-carlisle", "t": "Circle in the Sand — история хита Belinda Carlisle: текст, перевод и секреты", "i": "📁", "c": "drugoe"}, {"s": "city-car-driving-mercedes-w124", "t": "Вождение Mercedes W124 в городе: советы эксперта и секреты", "i": "📁", "c": "e-class"}, {"s": "civic-club-ru", "t": "Civic Club Russia: официальный клуб владельцев Honda Civic в РФ", "i": "📁", "c": "c-class"}, {"s": "citrus-cleaner-shine-systems", "t": "Citrus Cleaner Shine Systems: Эффективная чистка и полировка авто", "i": "📁", "c": "s-class"}, {"s": "cityup-ac-582-eagle", "t": "CityUp AC 582 Eagle: обзор, характеристики и особенности тюнинга", "i": "📁", "c": "e-class"}]