[{"s": "ebv-oshibka-mersedes", "t": "EBV ошибка Мерседес: причины, диагностика и методы устранения", "i": "📁", "c": "drugoe"}, {"s": "ebv-oshibka-mersedes-vito-638", "t": "Ошибка EBV Mercedes Vito 638: Причины и устранение", "i": "📁", "c": "vito"}, {"s": "ebu-mersedes-124", "t": "Mercedes W124: ЭБУ, диагностика и ремонт — полное руководство 2026", "i": "📁", "c": "e-class"}, {"s": "ebv-oshibka-mersedes-sprinter", "t": "EBV ошибка Mercedes Sprinter: причины, диагностика и устранение", "i": "📁", "c": "sprinter"}]