[{"s": "kh166-mercedes-benz", "t": "Mercedes-Benz X166: Полный обзор GLE первого поколения", "i": "📁", "c": "gle"}, {"s": "khendaj-stareks-ili-mersedes-vito", "t": "Хендай Старекс или Мерседес Вито: что выбрать для бизнеса?", "i": "📁", "c": "vito"}, {"s": "khendaj-kotoryj-pokhozh-na-mersedes", "t": "Хендай, похожий на Мерседес: обзор моделей Grandeur и Genesis", "i": "📁", "c": "drugoe"}, {"s": "khendaj-sonata-gls-v6", "t": "Хендай Соната GLS V6: Полный обзор, характеристики и тесты", "i": "📁", "c": "drugoe"}, {"s": "khonda-akkord-cl9-foto", "t": "Хонда Аккорд CL9 фото: обзор, характеристики и редкие снимки", "i": "📁", "c": "drugoe"}, {"s": "khonda-akkord-cl7", "t": "Honda Accord CL7: Обзор, характеристики и типичные проблемы", "i": "📁", "c": "drugoe"}, {"s": "khendaj-pokhozhaya-na-mersedes", "t": "Хендай похожая на Мерседес: сравнение Genesis и Mercedes-Benz", "i": "📁", "c": "s-class"}, {"s": "kharman-kardon-mersedes", "t": "Harman Kardon Mercedes: обзор, настройка и отличия от других систем", "i": "📁", "c": "drugoe"}, {"s": "kharakteristika-mersedes-w210", "t": "Mercedes W210: характеристики, особенности и слабые места E-Class 1995-2002", "i": "📁", "c": "e-class"}, {"s": "kharakteristiki-mersedes-s600", "t": "Mercedes S600: технические характеристики и особенности флагмана", "i": "📁", "c": "s-class"}, {"s": "khendaj-getts-gls", "t": "Hyundai Getz GLS: технические характеристики, плюсы и минусы модели", "i": "📁", "c": "drugoe"}, {"s": "khodovye-ogni-mersedes-aktros-mp3", "t": "Ходовые огни Mercedes Actros MP3: установка, неисправности, тюнинг", "i": "📁", "c": "drugoe"}, {"s": "khot-vils-premium-mersedes", "t": "Hot Wheels Premium Mercedes: коллекционные модели 2026 года", "i": "📁", "c": "drugoe"}, {"s": "kharakteristiki-tesla-model-s", "t": "Tesla Model S: технические характеристики 2026 года и секреты выбора", "i": "📁", "c": "s-class"}, {"s": "kharakteristiki-mersedes-211", "t": "Мерседес W211: технические характеристики и особенности модели", "i": "📁", "c": "e-class"}, {"s": "khendaj-sonata-gls", "t": "Hyundai Sonata GLS 2026: характеристики, цены и отзывы владельцев", "i": "📁", "c": "drugoe"}, {"s": "khendaj-pokhozhij-na-mersedes", "t": "Хендай похожий на Мерседес: какой модели отдать предпочтение?", "i": "📁", "c": "drugoe"}, {"s": "kholodilnik-samsung-rl52tebsl", "t": "Холодильник Samsung RL52TEBSL: обзор, характеристики, отзывы 2026", "i": "📁", "c": "b-class"}, {"s": "khronologiya-google-maps", "t": "Хронология Google Maps: как развивался сервис с 2005 по 2026 год", "i": "📁", "c": "drugoe"}, {"s": "khodovye-i-tormoznye-svojstva-izmeneny-mersedes-aktros", "t": "Ходовые и тормозные свойства Mercedes Actros: причины изменений и решения", "i": "📁", "c": "drugoe"}, {"s": "khomuty-clic-i-clic-r", "t": "Хомуты CLIC и CLIC-R: виды, применение и выбор для авто Mercedes-Benz", "i": "📁", "c": "a-class"}, {"s": "khonda-akkord-cl9", "t": "Honda Accord CL9: обзор, характеристики и особенности модели", "i": "📁", "c": "drugoe"}, {"s": "khomut-glushitelya-mersedes-aktros", "t": "Хомут глушителя Mercedes Actros: выбор, замена, советы эксперта", "i": "📁", "c": "drugoe"}, {"s": "kharakteristiki-nissan-almera-classic", "t": "Nissan Almera Classic: технические характеристики и особенности", "i": "📁", "c": "b-class"}, {"s": "khronologiya-google-karty", "t": "Хронология Google Карт: от запуска до AI-навигации (2005–2026)", "i": "📁", "c": "drugoe"}, {"s": "khendaj-elantra-gls-chto-oznachaet", "t": "Hyundai Elantra GLS: расшифровка маркировки и отличия от других версий", "i": "📁", "c": "drugoe"}, {"s": "kharlej-devidson-v-rod-muscle", "t": "Harley-Davidson V-Rod Muscle: Полный обзор, характеристики и отзывы владельцев", "i": "📁", "c": "drugoe"}, {"s": "kharakteristika-mersedes-e200", "t": "Mercedes E200: технические характеристики и особенности модели", "i": "📁", "c": "e-class"}, {"s": "kharakteristiki-mersedes-124", "t": "Мерседес W124: технические характеристики и особенности модели", "i": "📁", "c": "e-class"}, {"s": "kholodilnik-samsung-rl55tebsl-instruktsiya", "t": "Инструкция Samsung RL55TEBSL: настройка и уход за холодильником", "i": "📁", "c": "b-class"}, {"s": "khronologiya-google-kart", "t": "Хронология Google Карт: от Where 2 до Street View и AI-картографии", "i": "📁", "c": "drugoe"}, {"s": "khonda-akkord-cl1", "t": "Honda Accord CL1 (1997-2002): технические характеристики, проблемы и тюнинг", "i": "📁", "c": "drugoe"}, {"s": "khonda-cl-400", "t": "Honda CL 400: обзор, характеристики и отзывы владельцев (2026)", "i": "📁", "c": "drugoe"}, {"s": "kharakteristika-mersedes-banan", "t": "Mercedes-Benz W114 «Банан»: характеристики, особенности и секреты культового седана", "i": "📁", "c": "drugoe"}, {"s": "khomut-glushitelya-mersedes", "t": "Хомут глушителя Mercedes: выбор, замена и диагностика неисправностей", "i": "📁", "c": "drugoe"}, {"s": "kharakteristiki-mersedes-cls-63-amg", "t": "Mercedes CLS 63 AMG: технические характеристики и особенности (2026)", "i": "📁", "c": "cls"}]