[{"s": "kvadrotsikl-atv-classic-200-lux", "t": "ATV Classic 200 Lux: обзор, характеристики и советы по выбору квадроцикла", "i": "📁", "c": "drugoe"}, {"s": "kvkg-mersedes-w204", "t": "КВКГ Мерседес W204: Ремонт и замена генератора", "i": "📁", "c": "c-class"}, {"s": "kvadrotsikl-gladiator-f200-lux-otzyvy", "t": "Квадроцикл Gladiator F200 Lux: честные отзывы владельцев и обзор", "i": "📁", "c": "drugoe"}, {"s": "kvkg-mersedes-w204-271-motor", "t": "КВКГ Мерседес W204 271: Диагностика, замена и ремонт", "i": "📁", "c": "c-class"}, {"s": "kvadrotsikl-universal-atv-125-tm-classic", "t": "Квадроцикл Universal ATV 125 TM Classic: Полный обзор и тест", "i": "📁", "c": "drugoe"}, {"s": "kvadratnyj-mersedes-sedan", "t": "Квадратный Мерседес седан: История, модели и влияние на дизайн", "i": "📁", "c": "e-class"}, {"s": "kvadrotsikl-atv-classic-8", "t": "Квадроцикл ATV Classic 8: обзор, характеристики и отзывы 2026", "i": "📁", "c": "drugoe"}, {"s": "kvkg-chto-eto-mersedes", "t": "КВКГ что это Мерседес: расшифровка кода краски", "i": "📁", "c": "e-class"}, {"s": "kvadrotsikl-atv-classic-200-otzyvy", "t": "Квадроцикл ATV Classic 200: честные отзывы, плюсы и минусы", "i": "📁", "c": "drugoe"}, {"s": "kvkg-w204-m271", "t": "Двигатель M271 на Mercedes W204: Ресурс, проблемы и ремонт", "i": "📁", "c": "c-class"}, {"s": "kvkg-mersedes-w205", "t": "КВКГ Mercedes W205: расшифровка, неисправности и замена", "i": "📁", "c": "c-class"}, {"s": "kvadrotsikl-atv-classic-49-cc", "t": "Квадроцикл ATV Classic 49 cc: полный обзор, характеристики и настройка", "i": "📁", "c": "drugoe"}, {"s": "kvadrotsikl-cectek-gladiator-550", "t": "Квадроцикл Cectek Gladiator 550: полный обзор и характеристики", "i": "📁", "c": "drugoe"}, {"s": "kvkg-mersedes-chto-eto", "t": "KWG Mercedes: что это значит в документах и системе WDA", "i": "📁", "c": "drugoe"}, {"s": "kvadrotsikl-atv-classic-49-cc-kharakteristiki", "t": "Квадроцикл ATV Classic 49 cc: характеристики, плюсы и минусы", "i": "📁", "c": "drugoe"}, {"s": "kvkg-mersedes-271-motor", "t": "КВКГ Mercedes W271: двигатель M271 — характеристики, проблемы, тюнинг", "i": "📁", "c": "b-class"}, {"s": "kvadrotsikl-atv-classic-10-lux", "t": "ATV Classic 10 Lux: обзор квадроцикла, цены и отзывы 2026", "i": "📁", "c": "drugoe"}, {"s": "kvadrotsikl-cectek-gladiator", "t": "Квадроцикл Cectek Gladiator: обзор, характеристики и отзывы 2026", "i": "📁", "c": "drugoe"}, {"s": "kvk-800-dvigatel-mersedes", "t": "Двигатель OM640 (KVK 800) Mercedes: характеристики и проблемы", "i": "📁", "c": "e-class"}, {"s": "kvadratnyj-dzhip-mersedes", "t": "Квадратный джип Мерседес: G-Class, AMG и тюнинг", "i": "📁", "c": "g-class"}, {"s": "kvkg-mersedes-w212", "t": "КВКГ Мерседес W212: Диагностика и ремонт рулевого редуктора", "i": "📁", "c": "e-class"}]