[{"s": "wis-mercedes-online", "t": "WIS Mercedes Online: доступ к заводским схемам и мануалам", "i": "📁", "c": "drugoe"}, {"s": "windshield-glass-cleaner-tabletki-instruktsiya", "t": "Таблетки для омывателя лобового стекла: инструкция и рейтинг", "i": "📁", "c": "drugoe"}, {"s": "wis-onlajn-mercedes", "t": "WIS Online Mercedes: Полное руководство по работе с системой", "i": "📁", "c": "drugoe"}, {"s": "wifi-clock-esp8266", "t": "Умные часы на ESP8266: Сборка и прошивка WiFi Clock", "i": "📁", "c": "drugoe"}, {"s": "wireless-usb-dongle-50-kak-podklyuchit", "t": "Как подключить Wireless USB Dongle 5.0: Инструкция", "i": "📁", "c": "drugoe"}, {"s": "wis-asra-mercedes-online", "t": "wis asra mercedes online: Доступ к заводским схемам и ремонту", "i": "📁", "c": "drugoe"}, {"s": "wis-asra-mercedes", "t": "WIS Asra Mercedes: полный обзор системы WIS/ASRA", "i": "📁", "c": "drugoe"}, {"s": "wi-fi-keenetic-sprinter", "t": "Keenetic Sprinter: настройка Wi-Fi, скорость и проблемы подключения", "i": "📁", "c": "sprinter"}, {"s": "wingle-7-otzyvy", "t": "Wingle 7 отзывы: стоит ли покупать китайский пикап?", "i": "📁", "c": "drugoe"}, {"s": "wi-fi-router-keenetic-sprinter-ax3000", "t": "Keenetic Sprinter AX3000: обзор Wi-Fi 6 роутера", "i": "📁", "c": "drugoe"}, {"s": "windigo-motor-cleaner", "t": "Windigo Motor Cleaner: Мощь и чистота двигателя", "i": "📁", "c": "drugoe"}, {"s": "wis-mercedes-skachat", "t": "WIS Mercedes скачать: актуальные версии и установка", "i": "📁", "c": "drugoe"}, {"s": "wis-mersedes-onlajn", "t": "WIS Mercedes онлайн: полное руководство по работе с EPC", "i": "📁", "c": "drugoe"}, {"s": "wingle-7-great-wall", "t": "Great Wall Wingle 7: Полный обзор, характеристики и тест-драйв пикапа", "i": "📁", "c": "drugoe"}, {"s": "wireless-usb-dongle", "t": "Wireless USB Dongle: виды, настройка и выбор адаптера", "i": "📁", "c": "drugoe"}, {"s": "wis-mersedes-onlajn-besplatno", "t": "WIS Mercedes онлайн бесплатно: доступ к документации", "i": "📁", "c": "drugoe"}, {"s": "wi-fi-router-keenetic-sprinter-se", "t": "Keenetic Sprinter SE: обзор Wi-Fi роутера и настройка для дома", "i": "📁", "c": "b-class"}, {"s": "wis-mercedes-online-na-russkom", "t": "WIS Mercedes Online на русском: Полное руководство по ремонту", "i": "📁", "c": null}, {"s": "wi-fi-router-keenetic-sprinter", "t": "Keenetic Sprinter: настройка Wi-Fi роутера для дома и офиса", "i": "📁", "c": "s-class"}, {"s": "wingle-7-katalog-zapchastej", "t": "Каталог запчастей Wingle 7: оригинал, аналоги и где купить дешевле", "i": "📁", "c": "drugoe"}, {"s": "wide-angle-lens-videoregistrator", "t": "Wide Angle Lens в видеорегистраторах: как выбрать и настроить", "i": "📁", "c": "drugoe"}, {"s": "wi-fi-router-keenetic-sprinter-kn-3710", "t": "Keenetic Sprinter KN-3710: обзор, настройка и секреты Wi-Fi роутера", "i": "📁", "c": "s-class"}, {"s": "windows-doors-cleaner", "t": "Как очистить окна и двери без разводов: 7 профессиональных методов", "i": "📁", "c": "drugoe"}, {"s": "wisl-103-oshibki", "t": "Ошибка WISL 103 в Mercedes: причины и решения (2026)", "i": "📁", "c": "e-class"}, {"s": "wis-asra-mercedes-skachat", "t": "Как скачать и установить WIS ASRA для Mercedes: полное руководство", "i": "📁", "c": "drugoe"}, {"s": "wis-online-mercedes", "t": "WIS Online Mercedes: Полный гид по ремонту и диагностике", "i": "📁", "c": "drugoe"}, {"s": "windshield-glass-cleaner", "t": "Лучшие средства для очистки лобового стекла: ТОП-10 + советы экспертов", "i": "📁", "c": "s-class"}, {"s": "winde-servis-mersedes", "t": "Winde сервис Мерседес: коды ошибок, функции и диагностика", "i": "📁", "c": "drugoe"}, {"s": "wis-mersedes-skachat", "t": "WIS Mercedes скачать: актуальные версии и установка", "i": "📁", "c": "drugoe"}, {"s": "willson-body-glass-guard", "t": "Willson Body Glass Guard: полный обзор защитного покрытия", "i": "📁", "c": "drugoe"}, {"s": "wis-skachat-dlya-mersedes", "t": "Как скачать и установить WIS для Mercedes: полное руководство", "i": "📁", "c": "drugoe"}, {"s": "wingle-5-pikap", "t": "Wingle 5 пикап: обзор, характеристики и тесты надежности", "i": "📁", "c": "drugoe"}, {"s": "wis-asra-mercedes-skachat-torrent", "t": "Wis Asra Mercedes: скачать торрент прошивку и руководство", "i": "📁", "c": "drugoe"}]