[{"s": "www-glass-xl-ru", "t": "www glass xl ru: Обзор и характеристики автостекол", "i": "📁", "c": "drugoe"}, {"s": "www-mercedesmagazin-ru-otzyvy", "t": "www mercedesmagazin ru отзывы: правда и мифы о клубе", "i": "📁", "c": "drugoe"}, {"s": "www-oplatagosuslug-ru", "t": "Оплата госуслуг через www.oplata-gosuslug.ru: инструкция и нюансы 2026", "i": "📁", "c": "drugoe"}, {"s": "www-defender-global-com", "t": "Defender Global: обзор, отзывы и особенности заказа авто из США", "i": "📁", "c": "s-class"}, {"s": "www-spinningline-ru", "t": "SpinningLine.ru: обзор, отзывы и секреты выбора спиннингов 2026", "i": "📁", "c": "drugoe"}, {"s": "www-aoglonass-ru", "t": "AOGLONASS.RU: как проверить авто по ГЛОНАСС и GPS онлайн", "i": "📁", "c": "drugoe"}, {"s": "www-driveclickbank-ru-lichnyj-kabinet", "t": "DriveClickBank.ru: вход в личный кабинет и настройка аккаунта", "i": "📁", "c": "drugoe"}, {"s": "www-avito-ru-ofitsialnyj", "t": "Avito.ru официальный сайт: как отличить подделку от оригинала", "i": "📁", "c": "drugoe"}, {"s": "www-mercedes-benz-ru", "t": "Mercedes-Benz Russia: официальный сайт www.mercedes-benz.ru", "i": "📁", "c": "drugoe"}, {"s": "www-google-com-device", "t": "WWW.GOOGLE.COM/DEVICE: как управлять устройствами через Google?", "i": "📁", "c": "drugoe"}, {"s": "ww-avito-ru", "t": "Avito.ru: как пользоваться, секреты поиска и безопасность сделок", "i": "📁", "c": "drugoe"}, {"s": "www-avito-ru-obyavleniya-besplatnye", "t": "Avito объявления бесплатно: как разместить и продвинуть в 2026 году", "i": "📁", "c": "drugoe"}, {"s": "www-mercedesmagazin-ru", "t": "MercedesMagazin.ru: обзор, возможности и секреты портала для владельцев Mercedes", "i": "📁", "c": "drugoe"}, {"s": "www-avito-ru", "t": "Avito.ru: как пользоваться, SEO-продвижение и секреты эффективных объявлений", "i": "📁", "c": "drugoe"}, {"s": "www-prado-club-su-forum", "t": "www prado club su форум: Обзор сообщества и поиск аналогов", "i": "📁", "c": "s-class"}]